Metadata-Version: 1.0
Name: storescrapper
Version: 0.2.4
Summary: Web scrapping API for selected stores
Home-page: https://github.com/SoloTodo/storescrapper
Author: Vijay Khemlani
Author-email: vkhemlan@gmail.com
License: LICENSE.txt
Platform: UNKNOWN
